geodesix/__init__.py
geodesix/kinematics/__init__.py
geodesix/kinematics/jacobian.py
geodesix/lie/__init__.py
geodesix/lie/s3.py
geodesix/lie/se3.py
geodesix/lie/so3.py
geodesix/spatial/__init__.py
geodesix/spatial/screw.py
geodesix/util/__init__.py
geodesix/util/math.py
geodesix-0.1.0.dist-info/METADATA
geodesix-0.1.0.dist-info/WHEEL
geodesix-0.1.0.dist-info/licenses/LICENSE
geodesix-0.1.0.dist-info/RECORD
